iascan/__init__.py
iascan/main.py
iascan-2.7.dist-info/METADATA
iascan-2.7.dist-info/WHEEL
iascan-2.7.dist-info/entry_points.txt
iascan-2.7.dist-info/top_level.txt
iascan-2.7.dist-info/RECORD
