Metadata-Version: 2.1
Name: iascan
Version: 2.7
Summary: A simple IP scanner tool
Home-page: https://github.com/GeekMada/iascan.git
Author: Itibar Aheshman
Author-email: aheshman.itibar@gmail.com
Classifier: Programming Language :: Python :: 3
Classifier: License :: OSI Approved :: MIT License
Classifier: Operating System :: OS Independent
Requires-Python: >=3.6
Requires-Dist: requests
